ArchiveLibrary/__init__.py
ArchiveLibrary/keywords.py
ArchiveLibrary/utils.py
ArchiveLibrary/version.py
robotframework_archivelibrary-0.4.3.dist-info/METADATA
robotframework_archivelibrary-0.4.3.dist-info/WHEEL
robotframework_archivelibrary-0.4.3.dist-info/top_level.txt
robotframework_archivelibrary-0.4.3.dist-info/RECORD
