Metadata-Version: 2.1
Name: robotframework-archivelibrary
Version: 0.4.3
Summary: Robot Framework keyword library for handling ZIP files
Home-page: http://github.com/bulkan/robotframework-archivelibrary
Author: Bulkan Savun Evcimen
Author-email: bulkan@gmail.com
Maintainer: Luca Giovenzana
Maintainer-email: luca@giovenzana.org
License: Public Domain
Keywords: robotframework testing test automation zip files compressed
Platform: any
Classifier: Development Status :: 5 - Production/Stable
Classifier: License :: Public Domain
Classifier: Operating System :: OS Independent
Classifier: Programming Language :: Python
Classifier: Topic :: Software Development :: Testing
Provides-Extra: test
